api_client.py
config.py
main.py
selector.py
ui.py
commands/__init__.py
commands/auth.py
commands/chats.py
commands/notes.py
zen_ai_cli-1.0.2.dist-info/licenses/LICENSE
zen_ai_cli-1.0.2.dist-info/METADATA
zen_ai_cli-1.0.2.dist-info/WHEEL
zen_ai_cli-1.0.2.dist-info/entry_points.txt
zen_ai_cli-1.0.2.dist-info/top_level.txt
zen_ai_cli-1.0.2.dist-info/RECORD
