Metadata-Version: 2.4
Name: zen-ai-cli
Version: 1.0.2
Summary: A beautiful terminal interface for Zen AI
Author-email: Zen AI Team <your-email@example.com>
License-Expression: MIT
Project-URL: Homepage, https://github.com/joan-code6/zen_ai
Project-URL: Repository, https://github.com/joan-code6/zen_ai
Project-URL: Issues, https://github.com/joan-code6/zen_ai/issues
Keywords: cli,ai,terminal,chat,notes,tui
Classifier: Development Status :: 4 - Beta
Classifier: Environment :: Console
Classifier: Intended Audience :: End Users/Desktop
Classifier: Operating System :: OS Independent
Classifier: Programming Language :: Python :: 3
Classifier: Programming Language :: Python :: 3.10
Classifier: Programming Language :: Python :: 3.11
Classifier: Programming Language :: Python :: 3.12
Classifier: Programming Language :: Python :: 3.13
Classifier: Topic :: Communications :: Chat
Classifier: Topic :: Utilities
Requires-Python: >=3.10
License-File: LICENSE
Requires-Dist: httpx>=0.25.0
Requires-Dist: rich>=13.0.0
Requires-Dist: prompt_toolkit>=3.0.0
Requires-Dist: python-dotenv>=1.0.0
Dynamic: license-file
